Metadata-Version: 2.4
Name: solveig
Version: 0.6.3
Summary: An AI assistant that enables secure and extensible agentic behavior from any LLM in your terminal
Author: Francisco
License:                     GNU GENERAL PUBLIC LICENSE
Project-URL: Homepage, https://github.com/FSilveiraa/solveig
Project-URL: About, https://github.com/FSilveiraa/solveig/blob/main/docs/about.md
Project-URL: Roadmap, https://github.com/FSilveiraa/solveig/discussions/2
Keywords: ai,automation,security,llm,assistant
Classifier: Development Status :: 4 - Beta
Classifier: Intended Audience :: Developers
Classifier: Intended Audience :: End Users/Desktop
Classifier: License :: OSI Approved :: GNU General Public License v3 (GPLv3)
Classifier: Programming Language :: Python :: 3
Classifier: Programming Language :: Python :: 3.13
Classifier: Topic :: Scientific/Engineering :: Artificial Intelligence
Classifier: Topic :: Software Development :: Code Generators
Classifier: Topic :: Software Development :: Libraries :: Python Modules
Classifier: Topic :: Security
Classifier: Topic :: Terminals
Classifier: Environment :: Console
Classifier: Operating System :: OS Independent
Requires-Python: >=3.13
License-File: LICENSE
Requires-Dist: distro>=1.9.0
Requires-Dist: aiofiles>=25.1.0
Requires-Dist: instructor==1.13.0
Requires-Dist: openai>=1.108.0
Requires-Dist: pydantic>=2.11.0
Requires-Dist: tiktoken>=0.11.0
Requires-Dist: textual>=6.1.0
Requires-Dist: rich>=14.0.0
Provides-Extra: dev
Requires-Dist: setuptools>=61.0; extra == "dev"
Requires-Dist: anthropic>=0.68.0; extra == "dev"
Requires-Dist: google-generativeai>=0.8.5; extra == "dev"
Requires-Dist: pytest>=8.3.0; extra == "dev"
Requires-Dist: pytest-cov>=6.0.0; extra == "dev"
Requires-Dist: ruff>=0.8.0; extra == "dev"
Requires-Dist: mypy>=1.13.0; extra == "dev"
Provides-Extra: anthropic
Requires-Dist: anthropic>=0.68.0; extra == "anthropic"
Provides-Extra: google
Requires-Dist: google-generativeai>=0.8.5; extra == "google"
Dynamic: license-file
